symcollab/xor/__init__.py
symcollab/xor/ac.py
symcollab/xor/structure.py
symcollab/xor/xor.py
symcollab/xor/xorhelper.py
symcollab_xor-0.1.1.dist-info/METADATA
symcollab_xor-0.1.1.dist-info/WHEEL
symcollab_xor-0.1.1.dist-info/top_level.txt
symcollab_xor-0.1.1.dist-info/RECORD
