Metadata-Version: 2.1
Name: symcollab-xor
Version: 0.1.1
Summary: UNKNOWN
Home-page: https://github.com/symcollab/cryptosolve
Author: UNKNOWN
Author-email: UNKNOWN
License: UNKNOWN
Platform: UNKNOWN
Requires-Dist: symcollab-algebra
